Metadata-Version: 2.1
Name: text-new-wargame-git
Version: 2.0.0
Summary: It is a test pkg ignore. I just want to test whether I am able to prepare it
Home-page: https://github.com/imshadab/wargame
Author: Mohd Shadab Khan
Author-email: khanshadab96@yahoo.com
License: LICENSE.txt
Platform: UNKNOWN
Classifier: Programming Language :: Python :: 3
Classifier: License :: OSI Approved :: MIT License
Classifier: Operating System :: OS Independent
